{
  "name": "detox",
  "license": "MIT",
  "tags": ["cross","dom","xml","js","domtools","dtx","detox"],
  "description": "Detox - A cross-platform library for Haxe to make working with Xml and the DOM easy... similar to jQuery and friends, but works wherever Haxe works, in a more haxe-like way.",
  "contributors": ["jason"],
  "releasenote": "Use build class position rather than Context.currentPos() to make error messages a little more helpful.",
  "version": "0.17.0",
  "url": "https://github.com/jasononeil/detox",
  "classPath": "src/",
  "dependencies": {
    "selecthxml": "",
    "tink_macro": "",
    "beanhx": "0.11.1"
  }
}
